pynchrotron/__init__.py
pynchrotron/_version.py
pynchrotron/synchrotron.py
pynchrotron/synchrotron_kernel.py
pynchrotron/threeML_models.py
pynchrotron-1.0.0.dist-info/LICENSE
pynchrotron-1.0.0.dist-info/METADATA
pynchrotron-1.0.0.dist-info/WHEEL
pynchrotron-1.0.0.dist-info/top_level.txt
pynchrotron-1.0.0.dist-info/RECORD
