Metadata-Version: 2.1
Name: pynchrotron
Version: 1.0.0
Summary: computes synchrotron from cooling electrons
Home-page: https://github.com/grburgess/pynchrotron
Author: J. Michael Burgess
Author-email: jmichaelburgess@gmail.com
License: GPL
Project-URL: Bug Tracker, https://github.com/grburgess/pynchrotron/issues
Project-URL: Source Code, https://github.com/grburgess/pynchrotron
Platform: UNKNOWN
Classifier: Development Status :: 2 - Pre-Alpha
Classifier: Environment :: Console
Classifier: Intended Audience :: Science/Research
Classifier: License :: OSI Approved :: GNU General Public License v2 or later (GPLv2+)
Classifier: Operating System :: POSIX
Classifier: Programming Language :: Python :: 3.5
Classifier: Programming Language :: Python :: 3.6
Classifier: Programming Language :: Python :: 3.7
Classifier: Programming Language :: Python :: 3.8
Classifier: Topic :: Scientific/Engineering :: Physics
Requires-Dist: numba
Requires-Dist: numpy
Requires-Dist: astromodels
